hampy/__init__.py
hampy/detect.py
hampy/hamming.py
hampy/hamming_marker.py
hampy-1.4.2.dist-info/LICENSE
hampy-1.4.2.dist-info/METADATA
hampy-1.4.2.dist-info/WHEEL
hampy-1.4.2.dist-info/top_level.txt
hampy-1.4.2.dist-info/RECORD
