Metadata-Version: 2.1
Name: hampy
Version: 1.4.2
Summary: Simple Hamming Marker Detection using OpenCV
Home-page: https://github.com/pierre-rouanet/hampy
Author: Pierre Rouanet
Author-email: pierre.rouanet@gmail.com
License: GNU GENERAL PUBLIC LICENSE Version 3
Platform: UNKNOWN
License-File: LICENSE
Requires-Dist: numpy
Requires-Dist: matplotlib
Requires-Dist: scipy
